setup.py
crrunner/__init__.py
crrunner/crrunner.py
crrunner/event.py
crrunner/test_crrunner.py
crrunner.egg-info/PKG-INFO
crrunner.egg-info/SOURCES.txt
crrunner.egg-info/dependency_links.txt
crrunner.egg-info/requires.txt
crrunner.egg-info/top_level.txt
crrunner.egg-info/zip-safe